[
	{
		"model": "movies.actor",
		"pk": 2,
		"fields": {
			"name": "마크 해밀",
			"profile_path": "/9Wws35pCsT0KoZpiV4Gk5nbn9ZD.jpg"
		}
	},
	{
		"model": "movies.actor",
		"pk": 3,
		"fields": {
			"name": "해리슨 포드",
			"profile_path": "/5M7oN3sznp99hWYQ9sX0xheswWX.jpg"
		}
	},
	{
		"model": "movies.actor",
		"pk": 4,
		"fields": {
			"name": "캐리 피셔",
			"profile_path": "/veakLIqGCbG0ek3YKfrlzcF72CG.jpg"
		}
	},
	{
		"model": "movies.actor",
		"pk": 213001,
		"fields": {
			"name": "제니 슬레이트",
			"profile_path": "/hqLygFKiylb1hchgu113NP5r7iM.jpg"
		}
	},
	{
		"model": "movies.actor",
		"pk": 8210,
		"fields": {
			"name": "웨스 벤틀리",
			"profile_path": "/oDjtxTiEuCdyrcAtlCOEWUjhsaT.jpg"
		}
	},
	{
		"model": "movies.actor",
		"pk": 19,
		"fields": {
			"name": "앨리슨 제니",
			"profile_path": "/cDcB8mKP1GiIeoM3Qe7GIucs0iv.jpg"
		}
	},
	{
		"model": "movies.actor",
		"pk": 31,
		"fields": {
			"name": "톰 행크스",
			"profile_path": "/xndWFsBlClOJFRdhSt4NBwiPq2o.jpg"
		}
	},
	{
		"model": "movies.actor",
		"pk": 32,
		"fields": {
			"name": "로빈 라이트",
			"profile_path": "/8SWAGtDKEKWz3O5xV5Q31mZXUvL.jpg"
		}
	},
	{
		"model": "movies.actor",
		"pk": 172069,
		"fields": {
			"name": "채드윅 보스만",
			"profile_path": "/nL16SKfyP1b7Hk6LsuWiqMfbdb8.jpg"
		}
	},
	{
		"model": "movies.actor",
		"pk": 48,
		"fields": {
			"name": "숀 빈",
			"profile_path": "/kTjiABk3TJ3yI0Cto5RsvyT6V3o.jpg"
		}
	},
	{
		"model": "movies.actor",
		"pk": 62,
		"fields": {
			"name": "브루스 윌리스",
			"profile_path": "/caX3KtMU42EP3VLRFFBwqIIrch5.jpg"
		}
	},
	{
		"model": "movies.actor",
		"pk": 64,
		"fields": {
			"name": "게리 올드먼",
			"profile_path": "/2v9FVVBUrrkW2m3QOcYkuhq9A6o.jpg"
		}
	},
	{
		"model": "movies.actor",
		"pk": 65,
		"fields": {
			"name": "이안 홈",
			"profile_path": "/cOJDgvgj4nMec6Inzj1H5nugTO5.jpg"
		}
	},
	{
		"model": "movies.actor",
		"pk": 24647,
		"fields": {
			"name": "코니시 카츠유키",
			"profile_path": "/nYM5cH6U7cp4x9dIzW0enmEKmeV.jpg"
		}
	},
	{
		"model": "movies.actor",
		"pk": 99,
		"fields": {
			"name": "아만다 플러머",
			"profile_path": "/joHGUtEmXzJkH6ogEliiUKT9MNa.jpg"
		}
	},
	{
		"model": "movies.actor",
		"pk": 8293,
		"fields": {
			"name": "마리옹 코티야르",
			"profile_path": "/zChwjQ9D90fxx6cgWz5mUWHNd5b.jpg"
		}
	},
	{
		"model": "movies.actor",
		"pk": 103,
		"fields": {
			"name": "마크 러펄로",
			"profile_path": "/z3dvKqMNDQWk3QLxzumloQVR0pv.jpg"
		}
	},
	{
		"model": "movies.actor",
		"pk": 109,
		"fields": {
			"name": "일라이저 우드",
			"profile_path": "/7UKRbJBNG7mxBl2QQc5XsAh6F8B.jpg"
		}
	},
	{
		"model": "movies.actor",
		"pk": 110,
		"fields": {
			"name": "비고 모텐슨",
			"profile_path": "/vH5gVSpHAMhDaFWfh0Q7BG61O1y.jpg"
		}
	},
	{
		"model": "movies.actor",
		"pk": 112,
		"fields": {
			"name": "케이트 블란쳇",
			"profile_path": "/vq4vuAVhYngfzVNn8SbnG0JEy15.jpg"
		}
	},
	{
		"model": "movies.actor",
		"pk": 114,
		"fields": {
			"name": "올랜도 블룸",
			"profile_path": "/kKWJlX2tcjqceSfUxnV7Jle5Kt.jpg"
		}
	},
	{
		"model": "movies.actor",
		"pk": 1130611,
		"fields": {
			"name": "마츠오카 마유",
			"profile_path": "/ivbSQZKP5IJkzPv0nLJyxS9mMRo.jpg"
		}
	},
	{
		"model": "movies.actor",
		"pk": 2097275,
		"fields": {
			"name": "정지훈",
			"profile_path": "/b4JqQdspTwrtwavQ5e0uah6oyhG.jpg"
		}
	},
	{
		"model": "movies.actor",
		"pk": 134,
		"fields": {
			"name": "제이미 폭스",
			"profile_path": "/hPwCMEq6jLAidsXAX5BfoYgIfg2.jpg"
		}
	},
	{
		"model": "movies.actor",
		"pk": 138,
		"fields": {
			"name": "쿠엔틴 타란티노",
			"profile_path": "/1gjcpAa99FAOWGnrUvHEXXsRs7o.jpg"
		}
	},
	{
		"model": "movies.actor",
		"pk": 139,
		"fields": {
			"name": "우마 서먼",
			"profile_path": "/pGyACejvvLI6tB0gFQ2rCjwqKvd.jpg"
		}
	},
	{
		"model": "movies.actor",
		"pk": 65717,
		"fields": {
			"name": "존 햄",
			"profile_path": "/mrXE5fZbEDPc7BEE5G21J6qrwzi.jpg"
		}
	},
	{
		"model": "movies.actor",
		"pk": 1286328,
		"fields": {
			"name": "헤일리 루 리처드슨",
			"profile_path": "/3jWAFINe8W4KoHInnwxrPAsVc4Q.jpg"
		}
	},
	{
		"model": "movies.actor",
		"pk": 190,
		"fields": {
			"name": "클린트 이스트우드",
			"profile_path": "/dU35NnjZ4aGw5abIJe3WXVf3Eey.jpg"
		}
	},
	{
		"model": "movies.actor",
		"pk": 192,
		"fields": {
			"name": "모건 프리먼",
			"profile_path": "/905k0RFzH0Kd6gx8oSxRdnr6FL.jpg"
		}
	},
	{
		"model": "movies.actor",
		"pk": 65731,
		"fields": {
			"name": "샘 워싱턴",
			"profile_path": "/blKKsHlJIL9PmUQZB8f3YmMBW5Y.jpg"
		}
	},
	{
		"model": "movies.actor",
		"pk": 204,
		"fields": {
			"name": "케이트 윈슬렛",
			"profile_path": "/e3tdop3WhseRnn8KwMVLAV25Ybv.jpg"
		}
	},
	{
		"model": "movies.actor",
		"pk": 206,
		"fields": {
			"name": "짐 캐리",
			"profile_path": "/kuSlwTPsVlBMW0cvnFmbZce6PaV.jpg"
		}
	},
	{
		"model": "movies.actor",
		"pk": 228,
		"fields": {
			"name": "에드 해리스",
			"profile_path": "/ryF0KkljweLhPkQ70x6w3u9Qjjj.jpg"
		}
	},
	{
		"model": "movies.actor",
		"pk": 73968,
		"fields": {
			"name": "헨리 카빌",
			"profile_path": "/iWdKjMry5Pt7vmxU7bmOQsIUyHa.jpg"
		}
	},
	{
		"model": "movies.actor",
		"pk": 287,
		"fields": {
			"name": "브래드 피트",
			"profile_path": "/3UmLRKzI9fXONhyad2wdQ3JAKDO.jpg"
		}
	},
	{
		"model": "movies.actor",
		"pk": 1065297,
		"fields": {
			"name": "오노 켄쇼",
			"profile_path": "/wUYJ3HIeygHfh4rAqupE4RPoG3W.jpg"
		}
	},
	{
		"model": "movies.actor",
		"pk": 349,
		"fields": {
			"name": "스콧 글렌",
			"profile_path": "/t3t8UK98DnAPOZE8IGsEUCDjcjp.jpg"
		}
	},
	{
		"model": "movies.actor",
		"pk": 350,
		"fields": {
			"name": "로라 리니",
			"profile_path": "/ztQXGmNLzhDV22rAvcXzCG4d0cy.jpg"
		}
	},
	{
		"model": "movies.actor",
		"pk": 380,
		"fields": {
			"name": "로버트 드 니로",
			"profile_path": "/cT8htcckIuyI1Lqwt1CvD02ynTh.jpg"
		}
	},
	{
		"model": "movies.actor",
		"pk": 1024395,
		"fields": {
			"name": "마동석",
			"profile_path": "/zt1vx7FesNA4x6mTZtyzu2uco8E.jpg"
		}
	},
	{
		"model": "movies.actor",
		"pk": 8602,
		"fields": {
			"name": "앨리스 브라가",
			"profile_path": "/ykVmsm3For9dCBfWLRtTL0EU24b.jpg"
		}
	},
	{
		"model": "movies.actor",
		"pk": 16828,
		"fields": {
			"name": "크리스 에반스",
			"profile_path": "/3bOGNsHlrswhyW79uvIHH1V43JI.jpg"
		}
	},
	{
		"model": "movies.actor",
		"pk": 8635,
		"fields": {
			"name": "버스터 키튼",
			"profile_path": "/ejJz8YWn1Dr1PFn6E70NZ0oZ6o6.jpg"
		}
	},
	{
		"model": "movies.actor",
		"pk": 1876417,
		"fields": {
			"name": "이경진",
			"profile_path": "/xjgnqwNv2fYO789wTrDFqt071pa.jpg"
		}
	},
	{
		"model": "movies.actor",
		"pk": 90567,
		"fields": {
			"name": "세키 토모카즈",
			"profile_path": "/4N6i4cgtbeUj5AJd8kiBZ2BxxEJ.jpg"
		}
	},
	{
		"model": "movies.actor",
		"pk": 8654,
		"fields": {
			"name": "매튜 모딘",
			"profile_path": "/z974QEHL12qUvLyk6hlWGAmDgom.jpg"
		}
	},
	{
		"model": "movies.actor",
		"pk": 16847,
		"fields": {
			"name": "일라이 로스",
			"profile_path": "/qQTkpxzh1FlBGL1HD5hzdUMxv49.jpg"
		}
	},
	{
		"model": "movies.actor",
		"pk": 8691,
		"fields": {
			"name": "조 샐다나",
			"profile_path": "/iOVbUH20il632nj2v01NCtYYeSg.jpg"
		}
	},
	{
		"model": "movies.actor",
		"pk": 500,
		"fields": {
			"name": "톰 크루즈",
			"profile_path": "/8qBylBsQf4llkGrWR3qAsOtOU8O.jpg"
		}
	},
	{
		"model": "movies.actor",
		"pk": 1221114,
		"fields": {
			"name": "나카무라 유이치",
			"profile_path": "/wb8behVKjBHX9XXrEydvNINCYwH.jpg"
		}
	},
	{
		"model": "movies.actor",
		"pk": 514,
		"fields": {
			"name": "잭 니컬슨",
			"profile_path": "/6h12pZsgj3WWjMtykUgfLkLEBWz.jpg"
		}
	},
	{
		"model": "movies.actor",
		"pk": 74242,
		"fields": {
			"name": "쉬어 위햄",
			"profile_path": "/d3caK3l4UfbnzOxv95wLoFLZzMO.jpg"
		}
	},
	{
		"model": "movies.actor",
		"pk": 521,
		"fields": {
			"name": "마이클 폭스",
			"profile_path": "/2JB4FMgQmnhbBlQ4SxWFN9EIVDi.jpg"
		}
	},
	{
		"model": "movies.actor",
		"pk": 90633,
		"fields": {
			"name": "갤 가돗",
			"profile_path": "/plLfB60M5cJrnog8KvAKhI4UJuk.jpg"
		}
	},
	{
		"model": "movies.actor",
		"pk": 524,
		"fields": {
			"name": "나탈리 포트만",
			"profile_path": "/mqKHKayGsEK3TOZDHs3eUAhCP6V.jpg"
		}
	},
	{
		"model": "movies.actor",
		"pk": 529,
		"fields": {
			"name": "가이 피어스",
			"profile_path": "/hCzlUxrTLz3ntoPApW873sX0THf.jpg"
		}
	},
	{
		"model": "movies.actor",
		"pk": 540,
		"fields": {
			"name": "칼럼 키스 레니",
			"profile_path": "/zOeA4IR4xYde2VlDsHZy2SoPZkc.jpg"
		}
	},
	{
		"model": "movies.actor",
		"pk": 8741,
		"fields": {
			"name": "빅토르 쉬오스트롬",
			"profile_path": "/iGtT2mbmLt80YPk9lXJRSyxaEKW.jpg"
		}
	},
	{
		"model": "movies.actor",
		"pk": 16940,
		"fields": {
			"name": "제러미 아이언스",
			"profile_path": "/w8Ct1q02Ht3sWdOSqfp3B85TzT.jpg"
		}
	},
	{
		"model": "movies.actor",
		"pk": 569,
		"fields": {
			"name": "에단 호크",
			"profile_path": "/a7rgJl8TYUWAfJuM4fxbLHgD7BL.jpg"
		}
	},
	{
		"model": "movies.actor",
		"pk": 221773,
		"fields": {
			"name": "하야미 사오리",
			"profile_path": "/idFQBETcsRV7Uy7InV2x9e2iFWq.jpg"
		}
	},
	{
		"model": "movies.actor",
		"pk": 592,
		"fields": {
			"name": "조 터켈",
			"profile_path": "/tVuhSvNSKBhnDfEpsEGfjJl0H3G.jpg"
		}
	},
	{
		"model": "movies.actor",
		"pk": 115290,
		"fields": {
			"name": "이선균",
			"profile_path": "/mwF2HgyEF2UzxSvNRJEtbWlKbAj.jpg"
		}
	},
	{
		"model": "movies.actor",
		"pk": 1254052,
		"fields": {
			"name": "우치야마 코우키",
			"profile_path": "/sllSm3iZZWVLTBrDZQRtWrZUfEj.jpg"
		}
	},
	{
		"model": "movies.actor",
		"pk": 557743,
		"fields": {
			"name": "이용녀",
			"profile_path": "/vU2LIGOlVEUGfXfGWTdvEdz2rbT.jpg"
		}
	},
	{
		"model": "movies.actor",
		"pk": 8891,
		"fields": {
			"name": "존 트래볼타",
			"profile_path": "/sHjkE7GZbKAa9aZeiKrEBhMDT14.jpg"
		}
	},
	{
		"model": "movies.actor",
		"pk": 17127,
		"fields": {
			"name": "정석용",
			"profile_path": "/tyTSdGaVKotPmJXGNtz6fXoj8Tc.jpg"
		}
	},
	{
		"model": "movies.actor",
		"pk": 8944,
		"fields": {
			"name": "제이미 리 커티스",
			"profile_path": "/9KWvPVeiLOXlOGl0XVyHZtJWQtx.jpg"
		}
	},
	{
		"model": "movies.actor",
		"pk": 1442550,
		"fields": {
			"name": "루아나 바야미",
			"profile_path": "/iBzMJpbrOEKTQooyCOgoKrTW8Hi.jpg"
		}
	},
	{
		"model": "movies.actor",
		"pk": 2204431,
		"fields": {
			"name": "김미경",
			"profile_path": "/e1iTjY1FitE4vMu6s25Qmrf6qXc.jpg"
		}
	},
	{
		"model": "movies.actor",
		"pk": 123664,
		"fields": {
			"name": "김민희",
			"profile_path": "/zZ41nW0GJqesHB75hFP6qllPS9y.jpg"
		}
	},
	{
		"model": "movies.actor",
		"pk": 1442583,
		"fields": {
			"name": "박소담",
			"profile_path": "/gaDnEiMD5PClT9ARg1bSFyexbor.jpg"
		}
	},
	{
		"model": "movies.actor",
		"pk": 819,
		"fields": {
			"name": "에드워드 노튼",
			"profile_path": "/5XBzD5WuTyVQZeS4VI25z2moMeY.jpg"
		}
	},
	{
		"model": "movies.actor",
		"pk": 820,
		"fields": {
			"name": "에드워드 펄롱",
			"profile_path": "/e221dMIBgb6Lk092GIkHB9ohQF1.jpg"
		}
	},
	{
		"model": "movies.actor",
		"pk": 830,
		"fields": {
			"name": "조셉 코르테스",
			"profile_path": "/4Z2PvYRrpZ27xLKnDrtX6iRmJ3e.jpg"
		}
	},
	{
		"model": "movies.actor",
		"pk": 74568,
		"fields": {
			"name": "크리스 헴스워스",
			"profile_path": "/jpurJ9jAcLCYjgHHfYF32m3zJYm.jpg"
		}
	},
	{
		"model": "movies.actor",
		"pk": 533325,
		"fields": {
			"name": "바이쇼 치에코",
			"profile_path": "/b8ANR4WfdUZtoU4ktlnMFzbq759.jpg"
		}
	},
	{
		"model": "movies.actor",
		"pk": 854,
		"fields": {
			"name": "제임스 스튜어트",
			"profile_path": "/jam9DRhOuKomlr0vUXTamPoxPdk.jpg"
		}
	},
	{
		"model": "movies.actor",
		"pk": 880,
		"fields": {
			"name": "벤 애플렉",
			"profile_path": "/aTcqu8cI4wMohU17xTdqmXKTGrw.jpg"
		}
	},
	{
		"model": "movies.actor",
		"pk": 882,
		"fields": {
			"name": "리브 타일러",
			"profile_path": "/9IlcL0MWSNz8YLzqSooRHCQD4Dt.jpg"
		}
	},
	{
		"model": "movies.actor",
		"pk": 1254260,
		"fields": {
			"name": "오키츠 카즈유키",
			"profile_path": "/vgyaK5dAxhvzAi6LJM3ZyaJd4mJ.jpg"
		}
	},
	{
		"model": "movies.actor",
		"pk": 884,
		"fields": {
			"name": "스티브 부세미",
			"profile_path": "/lQKdHMxfYcCBOvwRKBAxPZVNtkg.jpg"
		}
	},
	{
		"model": "movies.actor",
		"pk": 887,
		"fields": {
			"name": "오웬 윌슨",
			"profile_path": "/op8sGD20k3EQZLR92XtaHoIbW0o.jpg"
		}
	},
	{
		"model": "movies.actor",
		"pk": 17288,
		"fields": {
			"name": "마이클 패스벤더",
			"profile_path": "/ygQSr3MsFzmYwJ343ZU4Fcc9voF.jpg"
		}
	},
	{
		"model": "movies.actor",
		"pk": 934,
		"fields": {
			"name": "러셀 크로우",
			"profile_path": "/mGTtPuwE8OR00tkJGmVLJmt8KpW.jpg"
		}
	},
	{
		"model": "movies.actor",
		"pk": 935,
		"fields": {
			"name": "코니 닐슨",
			"profile_path": "/lvQypTfeH2Gn2PTbzq6XkT2PLmn.jpg"
		}
	},
	{
		"model": "movies.actor",
		"pk": 937,
		"fields": {
			"name": "데릭 자코비",
			"profile_path": "/htc4eCYmNlVotcu8AFTbDiLBzsJ.jpg"
		}
	},
	{
		"model": "movies.actor",
		"pk": 938,
		"fields": {
			"name": "디몬 하운수",
			"profile_path": "/hco0KMbrxACYTmBfAkSzCf23CXV.jpg"
		}
	},
	{
		"model": "movies.actor",
		"pk": 123818,
		"fields": {
			"name": "권태원",
			"profile_path": "/c0i2M1l9sLM10dFARfy1MLM3mSE.jpg"
		}
	},
	{
		"model": "movies.actor",
		"pk": 123820,
		"fields": {
			"name": "김상호",
			"profile_path": "/t7Spp1HBl9dnb1OgkLvFz9fOidU.jpg"
		}
	},
	{
		"model": "movies.actor",
		"pk": 976,
		"fields": {
			"name": "제이슨 스타뎀",
			"profile_path": "/whNwkEQYWLFJA8ij0WyOOAD5xhQ.jpg"
		}
	},
	{
		"model": "movies.actor",
		"pk": 980,
		"fields": {
			"name": "비니 존스",
			"profile_path": "/tkYWG9gY2QpoBfOh4OWNz8yQfsw.jpg"
		}
	},
	{
		"model": "movies.actor",
		"pk": 148447,
		"fields": {
			"name": "오하라 사야카",
			"profile_path": "/4WQXLzj0gjYqkYFcTTxAkIwedvr.jpg"
		}
	},
	{
		"model": "movies.actor",
		"pk": 1003,
		"fields": {
			"name": "장 르노",
			"profile_path": "/q7dYamebioHRuvb9EWeSw8yTEfS.jpg"
		}
	},
	{
		"model": "movies.actor",
		"pk": 9206,
		"fields": {
			"name": "네브 캠벨",
			"profile_path": "/9fDbXBbrM6L10YrzDJUJowDt8U.jpg"
		}
	},
	{
		"model": "movies.actor",
		"pk": 1369100,
		"fields": {
			"name": "카미시라이시 모네",
			"profile_path": "/9gewWa82e0tviXmBB94bJdcEAEW.jpg"
		}
	},
	{
		"model": "movies.actor",
		"pk": 1037,
		"fields": {
			"name": "하비 카이텔",
			"profile_path": "/7P30hza1neYWW3r7rSQOC736K2Z.jpg"
		}
	},
	{
		"model": "movies.actor",
		"pk": 1038,
		"fields": {
			"name": "조디 포스터",
			"profile_path": "/AodjR16HMtbV8zZsUJdvJUSYxlo.jpg"
		}
	},
	{
		"model": "movies.actor",
		"pk": 1062,
		"fields": {
			"name": "크리스토퍼 로이드",
			"profile_path": "/nxVjpyb3UrfbPZnEyDNlQVlFAs5.jpg"
		}
	},
	{
		"model": "movies.actor",
		"pk": 1063,
		"fields": {
			"name": "리 톰프슨",
			"profile_path": "/85E9NTEfkRdUdK4kTrrnk5of25w.jpg"
		}
	},
	{
		"model": "movies.actor",
		"pk": 1064,
		"fields": {
			"name": "크리스핀 글로버",
			"profile_path": "/imBnLpSXvg61qDDdEfvL6R4ITKt.jpg"
		}
	},
	{
		"model": "movies.actor",
		"pk": 140335,
		"fields": {
			"name": "김유정",
			"profile_path": "/dqlafA1MFlJnZJutyT7trs4RpC4.jpg"
		}
	},
	{
		"model": "movies.actor",
		"pk": 83002,
		"fields": {
			"name": "제시카 채스테인",
			"profile_path": "/lodMzLKSdrPcBry6TdoDsMN3Vge.jpg"
		}
	},
	{
		"model": "movies.actor",
		"pk": 132157,
		"fields": {
			"name": "에즈라 밀러",
			"profile_path": "/6wmTpbYpmhthaxzM5ss3377F9IV.jpg"
		}
	},
	{
		"model": "movies.actor",
		"pk": 50266,
		"fields": {
			"name": "쉐마 무어",
			"profile_path": "/hO9pskl1sgKkghjCTa1eHVv5OMN.jpg"
		}
	},
	{
		"model": "movies.actor",
		"pk": 1121,
		"fields": {
			"name": "베니시오 델 토로",
			"profile_path": "/s1EVFX10YJZTcvkAAq4AcPniS3t.jpg"
		}
	},
	{
		"model": "movies.actor",
		"pk": 1385600,
		"fields": {
			"name": "노에미 메랑",
			"profile_path": "/mtJwBXFu0ggoUWXGq3xE1jv1hdD.jpg"
		}
	},
	{
		"model": "movies.actor",
		"pk": 1158,
		"fields": {
			"name": "알 파치노",
			"profile_path": "/fMDFeVf0pjopTJbyRSLFwNDm8Wr.jpg"
		}
	},
	{
		"model": "movies.actor",
		"pk": 1160,
		"fields": {
			"name": "미셸 파이퍼",
			"profile_path": "/oGUmQBU87QXAsnaGleYaAjAXSlj.jpg"
		}
	},
	{
		"model": "movies.actor",
		"pk": 1164,
		"fields": {
			"name": "머레이 아브라함",
			"profile_path": "/p2RYVGdrcP0m70BkkiKcwyrDeim.jpg"
		}
	},
	{
		"model": "movies.actor",
		"pk": 83122,
		"fields": {
			"name": "문소리",
			"profile_path": "/iXfIsmrzohNAAf2gyPCE06rJM1N.jpg"
		}
	},
	{
		"model": "movies.actor",
		"pk": 1204,
		"fields": {
			"name": "줄리아 로버츠",
			"profile_path": "/pahtuRDpaopvO6rH1RYS2omrO8L.jpg"
		}
	},
	{
		"model": "movies.actor",
		"pk": 17604,
		"fields": {
			"name": "제러미 레너",
			"profile_path": "/ycFVAVMliCCf0zXsKWNLBG3YxzK.jpg"
		}
	},
	{
		"model": "movies.actor",
		"pk": 17606,
		"fields": {
			"name": "이머전 푸츠",
			"profile_path": "/kJOUQP0I5HzyenTLWUTCdx6mIAk.jpg"
		}
	},
	{
		"model": "movies.actor",
		"pk": 1254614,
		"fields": {
			"name": "레슬리 오덤 주니어",
			"profile_path": "/pDA11JMNAGQGJo7nRpZHp7pdp9N.jpg"
		}
	},
	{
		"model": "movies.actor",
		"pk": 1245,
		"fields": {
			"name": "스칼릿 조핸슨",
			"profile_path": "/6NsMbJXRlDZuDzatN2akFdGuTvx.jpg"
		}
	},
	{
		"model": "movies.actor",
		"pk": 1246,
		"fields": {
			"name": "에밀리 모티머",
			"profile_path": "/eh0AebcU5ag535e3KLb6ydWR09d.jpg"
		}
	},
	{
		"model": "movies.actor",
		"pk": 34027,
		"fields": {
			"name": "스테파니아 산드렐리",
			"profile_path": "/aPmAstwHeEyN17UDKcSJf4OGBEQ.jpg"
		}
	},
	{
		"model": "movies.actor",
		"pk": 1283,
		"fields": {
			"name": "헬레나 본햄 카터",
			"profile_path": "/DDeITcCpnBd0CkAIRPhggy9bt5.jpg"
		}
	},
	{
		"model": "movies.actor",
		"pk": 34053,
		"fields": {
			"name": "아나 바헤네르",
			"profile_path": "/1UteQMIFBSdcYpZ5zDPI2VNOQYU.jpg"
		}
	},
	{
		"model": "movies.actor",
		"pk": 3728650,
		"fields": {
			"name": "윤이레",
			"profile_path": "/uKrJzryFpP2UCUoaV93OgXLohRx.jpg"
		}
	},
	{
		"model": "movies.actor",
		"pk": 1254671,
		"fields": {
			"name": "카야노 아이",
			"profile_path": "/l8ywp387rfdAS7mOExe3cEZnsk0.jpg"
		}
	},
	{
		"model": "movies.actor",
		"pk": 1254672,
		"fields": {
			"name": "세토 아사미",
			"profile_path": "/iKKCPgKrNd4pJ0iBOC1SBZy2Y4Y.jpg"
		}
	},
	{
		"model": "movies.actor",
		"pk": 1327,
		"fields": {
			"name": "이안 맥켈런",
			"profile_path": "/5cnnnpnJG6TiYUSS7qgJheUZgnv.jpg"
		}
	},
	{
		"model": "movies.actor",
		"pk": 1330,
		"fields": {
			"name": "도미닉 모나한",
			"profile_path": "/7X0JzecoAwLXyftU1p0Ha5D9BpU.jpg"
		}
	},
	{
		"model": "movies.actor",
		"pk": 1331,
		"fields": {
			"name": "휴고 위빙",
			"profile_path": "/kkkZx3qoLA8oilMSCGT4soDqXPu.jpg"
		}
	},
	{
		"model": "movies.actor",
		"pk": 1333,
		"fields": {
			"name": "앤디 서키스",
			"profile_path": "/eNGqhebQ4cDssjVeNFrKtUvweV5.jpg"
		}
	},
	{
		"model": "movies.actor",
		"pk": 1418580,
		"fields": {
			"name": "이동휘",
			"profile_path": "/1cZ40lS8BomxgOl2obltRsiefZ7.jpg"
		}
	},
	{
		"model": "movies.actor",
		"pk": 26076,
		"fields": {
			"name": "빌리 파이퍼",
			"profile_path": "/gBduwAWEZ1bwuL6f7cjMzBvKlJz.jpg"
		}
	},
	{
		"model": "movies.actor",
		"pk": 9705,
		"fields": {
			"name": "사쿠라이 타카히로",
			"profile_path": "/8s8owcKmpRAuhzEGjSdRpztthUg.jpg"
		}
	},
	{
		"model": "movies.actor",
		"pk": 9720,
		"fields": {
			"name": "이시카와 히데오",
			"profile_path": "/gEjEDNGt3CHsyzFQdNqewZVbh0.jpg"
		}
	},
	{
		"model": "movies.actor",
		"pk": 9726,
		"fields": {
			"name": "스즈무라 켄이치",
			"profile_path": "/vFqjmIjxfgBkh3ZmUin7QETV0sy.jpg"
		}
	},
	{
		"model": "movies.actor",
		"pk": 1418762,
		"fields": {
			"name": "정지소",
			"profile_path": "/3Teyw2Fzww30MvuOa3qtShIB4kd.jpg"
		}
	},
	{
		"model": "movies.actor",
		"pk": 1579,
		"fields": {
			"name": "매기 질렌할",
			"profile_path": "/qxgM5LzzG4uWTprCL3gBVVJ2Q1K.jpg"
		}
	},
	{
		"model": "movies.actor",
		"pk": 34374,
		"fields": {
			"name": "카가와 쿄코",
			"profile_path": "/q47wPwySJvhj6HQoYb7ON1TjbcV.jpg"
		}
	},
	{
		"model": "movies.actor",
		"pk": 1631814,
		"fields": {
			"name": "필리파 수",
			"profile_path": "/1oKShCBjS2wxeAFqPuO2XSrpa5w.jpg"
		}
	},
	{
		"model": "movies.actor",
		"pk": 1620,
		"fields": {
			"name": "양자경",
			"profile_path": "/6oxvfyrrM3YmhgFZSqc8ESqPZoC.jpg"
		}
	},
	{
		"model": "movies.actor",
		"pk": 1622,
		"fields": {
			"name": "장첸",
			"profile_path": "/7GHGozSsjERpQwvVwIhd1i6Yl7Y.jpg"
		}
	},
	{
		"model": "movies.actor",
		"pk": 9824,
		"fields": {
			"name": "다이앤 크루거",
			"profile_path": "/aScr0aXsTzLIO6bkB82YUuYj4PT.jpg"
		}
	},
	{
		"model": "movies.actor",
		"pk": 992869,
		"fields": {
			"name": "사쿠라 아야네",
			"profile_path": "/yPbTmntASE9psPIMhNGU5oo6vIH.jpg"
		}
	},
	{
		"model": "movies.actor",
		"pk": 18022,
		"fields": {
			"name": "지나 맥키",
			"profile_path": "/rHL7GGeFZ2x9PbFL2P3hVkLfvAS.jpg"
		}
	},
	{
		"model": "movies.actor",
		"pk": 1640,
		"fields": {
			"name": "스텔란 스카스가드",
			"profile_path": "/x78BtYHElirO7Iw8bL4m8CnzRDc.jpg"
		}
	},
	{
		"model": "movies.actor",
		"pk": 1164931,
		"fields": {
			"name": "한 메구미",
			"profile_path": "/52XQZeQRl8GkNZtqUHl17zWuZpD.jpg"
		}
	},
	{
		"model": "movies.actor",
		"pk": 1771,
		"fields": {
			"name": "조반니 리비시",
			"profile_path": "/xJrjoGhAfufROCiG2C86uYYjqpP.jpg"
		}
	},
	{
		"model": "movies.actor",
		"pk": 34546,
		"fields": {
			"name": "마크 거티스",
			"profile_path": "/rdinP6RQwKBab7BawJDBzF1I7Qz.jpg"
		}
	},
	{
		"model": "movies.actor",
		"pk": 1810,
		"fields": {
			"name": "히스 레저",
			"profile_path": "/5Y9HnYYa9jF4NunY9lSgJGjSe8E.jpg"
		}
	},
	{
		"model": "movies.actor",
		"pk": 1812,
		"fields": {
			"name": "미셸 윌리엄스",
			"profile_path": "/jn3BVMVbIptz2gc6Fhxo1qwJVvW.jpg"
		}
	},
	{
		"model": "movies.actor",
		"pk": 1813,
		"fields": {
			"name": "앤 해서웨이",
			"profile_path": "/tLelKoPNiyJCSEtQTz1FGv4TLGc.jpg"
		}
	},
	{
		"model": "movies.actor",
		"pk": 1817,
		"fields": {
			"name": "린다 카델리니",
			"profile_path": "/bcycvynDprC1rrhBNrnBjn5uOUd.jpg"
		}
	},
	{
		"model": "movies.actor",
		"pk": 1892,
		"fields": {
			"name": "맷 데이먼",
			"profile_path": "/At3JgvaNeEN4Z4ESKlhhes85Xo3.jpg"
		}
	},
	{
		"model": "movies.actor",
		"pk": 1893,
		"fields": {
			"name": "케이시 애플렉",
			"profile_path": "/vD5MtCjHPHpmU9XNn74EPGMHT7o.jpg"
		}
	},
	{
		"model": "movies.actor",
		"pk": 1896,
		"fields": {
			"name": "돈 치들",
			"profile_path": "/bynmDXiegMDjttb6x7I3ye2bCO1.jpg"
		}
	},
	{
		"model": "movies.actor",
		"pk": 10112,
		"fields": {
			"name": "유지태",
			"profile_path": "/gGGV2gc0orgssYJ0Q9MSomdYo2I.jpg"
		}
	},
	{
		"model": "movies.actor",
		"pk": 1979,
		"fields": {
			"name": "케빈 스페이시",
			"profile_path": "/dlVRkUYKyZdJ39AN55cY1LoyXAP.jpg"
		}
	},
	{
		"model": "movies.actor",
		"pk": 10182,
		"fields": {
			"name": "빙 레임스",
			"profile_path": "/4gpLVNKPZlVucc4fT2fSZ7DksTK.jpg"
		}
	},
	{
		"model": "movies.actor",
		"pk": 2377671,
		"fields": {
			"name": "박정우",
			"profile_path": "/7euKnxnUz6HqjkAHsSLy2dsPvRg.jpg"
		}
	},
	{
		"model": "movies.actor",
		"pk": 10205,
		"fields": {
			"name": "시고니 위버",
			"profile_path": "/flfhep27iBxseZIlxOMHt6zJFX1.jpg"
		}
	},
	{
		"model": "movies.actor",
		"pk": 59373,
		"fields": {
			"name": "멜라니 티에리",
			"profile_path": "/dtzfVWfyWgnlgwpzgA4uXDrBcTI.jpg"
		}
	},
	{
		"model": "movies.actor",
		"pk": 42993,
		"fields": {
			"name": "마틴 도노반",
			"profile_path": "/wTCmpcmd8mcAbsX6Yc7zFs2J98Q.jpg"
		}
	},
	{
		"model": "movies.actor",
		"pk": 2037,
		"fields": {
			"name": "킬리언 머피",
			"profile_path": "/i8dOTC0w6V274ev5iAAvo4Ahhpr.jpg"
		}
	},
	{
		"model": "movies.actor",
		"pk": 1492982,
		"fields": {
			"name": "리에리",
			"profile_path": "/6S7G3FZnma2vo4B8ODqAdbeRKda.jpg"
		}
	},
	{
		"model": "movies.actor",
		"pk": 1492992,
		"fields": {
			"name": "우치다 유마",
			"profile_path": "/tfOQOXhENBO5VFgwl8xiJNZb0pE.jpg"
		}
	},
	{
		"model": "movies.actor",
		"pk": 59410,
		"fields": {
			"name": "밥 오든커크",
			"profile_path": "/rF0Lb6SBhGSTvjRffmlKRSeI3jE.jpg"
		}
	},
	{
		"model": "movies.actor",
		"pk": 206869,
		"fields": {
			"name": "쉘비 라바라",
			"profile_path": "/ouMiEKlhCj2LFKEQtI6fGRMDemF.jpg"
		}
	},
	{
		"model": "movies.actor",
		"pk": 1239110,
		"fields": {
			"name": "미즈하시 카오리",
			"profile_path": "/eDhVZ9en7T4lvsQ99OkRizroSQd.jpg"
		}
	},
	{
		"model": "movies.actor",
		"pk": 1591370,
		"fields": {
			"name": "서현우",
			"profile_path": "/i5HP0n06Y5GIZfpsbibFQWAcUjV.jpg"
		}
	},
	{
		"model": "movies.actor",
		"pk": 1288294,
		"fields": {
			"name": "쿠보 유리카",
			"profile_path": "/tpzwj1J6HRq2H6xZjM5Irg7FzT2.jpg"
		}
	},
	{
		"model": "movies.actor",
		"pk": 34923,
		"fields": {
			"name": "타나카 아츠코",
			"profile_path": "/pXcJZCWA9uzZLH7vqU8M6KpAP3Z.jpg"
		}
	},
	{
		"model": "movies.actor",
		"pk": 2157,
		"fields": {
			"name": "로빈 윌리엄스",
			"profile_path": "/iYdeP6K0qz44Wg2Nw9LPJGMBkQ5.jpg"
		}
	},
	{
		"model": "movies.actor",
		"pk": 75913,
		"fields": {
			"name": "하정우",
			"profile_path": "/alHcDyLYbc6C2X9yOHw8mNHZVGu.jpg"
		}
	},
	{
		"model": "movies.actor",
		"pk": 10402,
		"fields": {
			"name": "알라나 우바치",
			"profile_path": "/p2sIpgftEIkhPrrpgu8wW8XEpDg.jpg"
		}
	},
	{
		"model": "movies.actor",
		"pk": 2231,
		"fields": {
			"name": "새뮤얼 잭슨",
			"profile_path": "/nCJJ3NVksYNxIzEHcyC1XziwPVj.jpg"
		}
	},
	{
		"model": "movies.actor",
		"pk": 2282,
		"fields": {
			"name": "벤 킹즐리",
			"profile_path": "/vQtBqpF2HDdzbfXHDzR4u37i1Ac.jpg"
		}
	},
	{
		"model": "movies.actor",
		"pk": 1296667,
		"fields": {
			"name": "우치다 마아야",
			"profile_path": "/tQAV6JsPWQ4H9u4kg1iuL5TKIif.jpg"
		}
	},
	{
		"model": "movies.actor",
		"pk": 936275,
		"fields": {
			"name": "유우키 아오이",
			"profile_path": "/4kHNZSUIux52UU2BD3H6b5c5ymZ.jpg"
		}
	},
	{
		"model": "movies.actor",
		"pk": 2395,
		"fields": {
			"name": "우피 골드버그",
			"profile_path": "/78LZMMzNUJVfLI1MObxejScwZz5.jpg"
		}
	},
	{
		"model": "movies.actor",
		"pk": 149894,
		"fields": {
			"name": "카지 유우키",
			"profile_path": "/8wKdPV11IwowfwoqGqMMNt9hmp6.jpg"
		}
	},
	{
		"model": "movies.actor",
		"pk": 1255881,
		"fields": {
			"name": "최우식",
			"profile_path": "/bIdt6LrqMpGQtGTZ1gmji6eGzTH.jpg"
		}
	},
	{
		"model": "movies.actor",
		"pk": 2524,
		"fields": {
			"name": "톰 하디",
			"profile_path": "/sGMA6pA2D6X0gun49igJT3piHs3.jpg"
		}
	},
	{
		"model": "movies.actor",
		"pk": 10730,
		"fields": {
			"name": "로완 앳킨슨",
			"profile_path": "/uxqBoDQoDJ8cdkeB1hT56QkA3b5.jpg"
		}
	},
	{
		"model": "movies.actor",
		"pk": 240145,
		"fields": {
			"name": "한효주",
			"profile_path": "/4E7NuJsR7AnMYAefFSHkj4cftdf.jpg"
		}
	},
	{
		"model": "movies.actor",
		"pk": 84505,
		"fields": {
			"name": "히라타 히로아키",
			"profile_path": "/mMWEdlssJm3TVuXW4Wb7pQeX20Z.jpg"
		}
	},
	{
		"model": "movies.actor",
		"pk": 84508,
		"fields": {
			"name": "코야스 타케히토",
			"profile_path": "/8uBkNDKPNmp9JWgMUI02NVyfhi1.jpg"
		}
	},
	{
		"model": "movies.actor",
		"pk": 18997,
		"fields": {
			"name": "브라이스 달라스 하워드",
			"profile_path": "/qQX1rhQaJ1G8eMG2RknFKiXfNRc.jpg"
		}
	},
	{
		"model": "movies.actor",
		"pk": 150125,
		"fields": {
			"name": "주지훈",
			"profile_path": "/7PYfUrBBXhYv5PIsTalJhjbRteg.jpg"
		}
	},
	{
		"model": "movies.actor",
		"pk": 19119,
		"fields": {
			"name": "멜라니 로랑",
			"profile_path": "/i99ogEo4gQyanCmHWYYoS6hsUqL.jpg"
		}
	},
	{
		"model": "movies.actor",
		"pk": 27319,
		"fields": {
			"name": "크리스토프 발츠",
			"profile_path": "/2Hhztd4mUEV9Y25rfkXDwzL9QI9.jpg"
		}
	},
	{
		"model": "movies.actor",
		"pk": 2778,
		"fields": {
			"name": "데니스 호퍼",
			"profile_path": "/3Hg8mkb1RxqNhDOofzHdr0PoufH.jpg"
		}
	},
	{
		"model": "movies.actor",
		"pk": 11008,
		"fields": {
			"name": "레베카 로미즌",
			"profile_path": "/5Jgmk7S3JxDUhdVLUFHUaJ42ovt.jpg"
		}
	},
	{
		"model": "movies.actor",
		"pk": 117504,
		"fields": {
			"name": "윤진서",
			"profile_path": "/5br9jHiVLUTmiNxqswpmDg7Zowb.jpg"
		}
	},
	{
		"model": "movies.actor",
		"pk": 1919754,
		"fields": {
			"name": "이마다 미오",
			"profile_path": "/f7gPq6gv3LDrs3eN0FJY5hGpfyG.jpg"
		}
	},
	{
		"model": "movies.actor",
		"pk": 1190668,
		"fields": {
			"name": "티모시 샬라메",
			"profile_path": "/fWcf1b3CEybhnE53xLpeAEl6WYJ.jpg"
		}
	},
	{
		"model": "movies.actor",
		"pk": 2829,
		"fields": {
			"name": "안제이 세베린",
			"profile_path": "/uYohJvqAai28Piqa0eEs6zAeFer.jpg"
		}
	},
	{
		"model": "movies.actor",
		"pk": 11086,
		"fields": {
			"name": "마이클 아이언사이드",
			"profile_path": "/mzHmxtKcMJjDqWxKd67mKQJFW1B.jpg"
		}
	},
	{
		"model": "movies.actor",
		"pk": 551776,
		"fields": {
			"name": "츠가와 마사히코",
			"profile_path": "/nuFYKbIdPZy58HkK7jqgRYh9Jik.jpg"
		}
	},
	{
		"model": "movies.actor",
		"pk": 35705,
		"fields": {
			"name": "레지나 홀",
			"profile_path": "/jiFZ4xNrvUUZLBHnJu71CvdN4kj.jpg"
		}
	},
	{
		"model": "movies.actor",
		"pk": 117642,
		"fields": {
			"name": "제이슨 모모아",
			"profile_path": "/3q2iVSCX8EVQkuY2n3OWgXBnnNT.jpg"
		}
	},
	{
		"model": "movies.actor",
		"pk": 2975,
		"fields": {
			"name": "로런스 피시번",
			"profile_path": "/8suOhUmPbfKqDQ17jQ1Gy0mI3P4.jpg"
		}
	},
	{
		"model": "movies.actor",
		"pk": 27578,
		"fields": {
			"name": "엘렌 페이지",
			"profile_path": "/596bLvD4iEz8VGc6TOEhzmPwTMe.jpg"
		}
	},
	{
		"model": "movies.actor",
		"pk": 527313,
		"fields": {
			"name": "테이사 파미가",
			"profile_path": "/kC2Movbs6uEF8DdDhvyHizQHuru.jpg"
		}
	},
	{
		"model": "movies.actor",
		"pk": 3035,
		"fields": {
			"name": "제리 오코넬",
			"profile_path": "/p2zcFeDIKUrPrbT5ODqoLifdN3Q.jpg"
		}
	},
	{
		"model": "movies.actor",
		"pk": 1772522,
		"fields": {
			"name": "미야모토 유메",
			"profile_path": "/1bpMweFhnzx40CbVP8aU05H8iaJ.jpg"
		}
	},
	{
		"model": "movies.actor",
		"pk": 1993723,
		"fields": {
			"name": "조은형",
			"profile_path": "/k72sQ6tq60e8vk2R8sFTe1fHV1H.jpg"
		}
	},
	{
		"model": "movies.actor",
		"pk": 3084,
		"fields": {
			"name": "말론 브란도",
			"profile_path": "/fuTEPMsBtV1zE98ujPONbKiYDc2.jpg"
		}
	},
	{
		"model": "movies.actor",
		"pk": 3087,
		"fields": {
			"name": "로버트 듀발",
			"profile_path": "/ybMmK25h4IVtfE7qrnlVp47RQlh.jpg"
		}
	},
	{
		"model": "movies.actor",
		"pk": 85008,
		"fields": {
			"name": "설경구",
			"profile_path": "/9SqQcvVUPUziK37i5jIeUoqSOMB.jpg"
		}
	},
	{
		"model": "movies.actor",
		"pk": 19492,
		"fields": {
			"name": "바이올라 데이비스",
			"profile_path": "/1QnmK4NBHN8tqVE3bxAzVSOUh80.jpg"
		}
	},
	{
		"model": "movies.actor",
		"pk": 3124,
		"fields": {
			"name": "발레리아 골리노",
			"profile_path": "/k7LQlRNI2YU3u6QGlvAMNbhq3AA.jpg"
		}
	},
	{
		"model": "movies.actor",
		"pk": 11317,
		"fields": {
			"name": "나타샤 맥켈혼",
			"profile_path": "/9pxaoasotR1pdCXYSfN1pkm0geO.jpg"
		}
	},
	{
		"model": "movies.actor",
		"pk": 3129,
		"fields": {
			"name": "팀 로스",
			"profile_path": "/qSizF2i9gz6c6DbAC5RoIq8sVqX.jpg"
		}
	},
	{
		"model": "movies.actor",
		"pk": 93252,
		"fields": {
			"name": "김해숙",
			"profile_path": "/gbWb5gXuhGCnTSogCrmMPD65F8w.jpg"
		}
	},
	{
		"model": "movies.actor",
		"pk": 3149,
		"fields": {
			"name": "마릴린 먼로",
			"profile_path": "/vcp6rHL2sZWdlJQDEWsEe0jAAe1.jpg"
		}
	},
	{
		"model": "movies.actor",
		"pk": 1248340,
		"fields": {
			"name": "토마츠 하루카",
			"profile_path": "/geVvuA2zMGE5xzfc20aDelJSelu.jpg"
		}
	},
	{
		"model": "movies.actor",
		"pk": 1248374,
		"fields": {
			"name": "에구치 타쿠야",
			"profile_path": "/1quDVJq7x5mZMvZaIXeypQlDaRN.jpg"
		}
	},
	{
		"model": "movies.actor",
		"pk": 3197,
		"fields": {
			"name": "톰 시즈모어",
			"profile_path": "/soINOuacuiThRb2LyPD4tTWve7C.jpg"
		}
	},
	{
		"model": "movies.actor",
		"pk": 19588,
		"fields": {
			"name": "이리노 미유",
			"profile_path": "/dcZ4IJX8CBcJzxy8hhKFXv59LDE.jpg"
		}
	},
	{
		"model": "movies.actor",
		"pk": 3223,
		"fields": {
			"name": "로버트 다우니 주니어",
			"profile_path": "/im9SAqJPZKEbVZGmjXuLI4O7RvM.jpg"
		}
	},
	{
		"model": "movies.actor",
		"pk": 1256603,
		"fields": {
			"name": "하나에 나츠키",
			"profile_path": "/A1lGrpBEdAUxZA7RoAw4Zr4ved3.jpg"
		}
	},
	{
		"model": "movies.actor",
		"pk": 2223265,
		"fields": {
			"name": "이양천새",
			"profile_path": "/d7y9zz1e5PDstH9PaLFXSXKaXIC.jpg"
		}
	},
	{
		"model": "movies.actor",
		"pk": 3265,
		"fields": {
			"name": "엘리 웰라치",
			"profile_path": "/880EvYjyIG9BcrM3Jfof0QofmRe.jpg"
		}
	},
	{
		"model": "movies.actor",
		"pk": 68816,
		"fields": {
			"name": "아델 에넬",
			"profile_path": "/uf2BVprWBZB7hxv0lj1RO48EDEZ.jpg"
		}
	},
	{
		"model": "movies.actor",
		"pk": 1666292,
		"fields": {
			"name": "아카네야 히미카",
			"profile_path": "/vH13pkAhod0GuFqDQeYXX55TKd6.jpg"
		}
	},
	{
		"model": "movies.actor",
		"pk": 3380,
		"fields": {
			"name": "베티 데이비스",
			"profile_path": "/h8JJeSEB7jc6Ce33Lh7XDQfXaVr.jpg"
		}
	},
	{
		"model": "movies.actor",
		"pk": 77180,
		"fields": {
			"name": "지대한",
			"profile_path": "/9aoOX8p2oxUAwOaT8jT6GWfjs01.jpg"
		}
	},
	{
		"model": "movies.actor",
		"pk": 77182,
		"fields": {
			"name": "김병옥",
			"profile_path": "/oGVs2OmYTyXR0KT9xvzVWCAKx8t.jpg"
		}
	},
	{
		"model": "movies.actor",
		"pk": 77183,
		"fields": {
			"name": "오태경",
			"profile_path": "/yhjx0z0Q4RJtxDewQz5wFWDMUax.jpg"
		}
	},
	{
		"model": "movies.actor",
		"pk": 77188,
		"fields": {
			"name": "오달수",
			"profile_path": "/hd72oGjq0YKYdgZKMnqtV00MV28.jpg"
		}
	},
	{
		"model": "movies.actor",
		"pk": 3490,
		"fields": {
			"name": "애드리언 브로디",
			"profile_path": "/1dBItgLFBNGEXnI48VvnnN2vFaX.jpg"
		}
	},
	{
		"model": "movies.actor",
		"pk": 3491,
		"fields": {
			"name": "토마스 크레취만",
			"profile_path": "/7M0P39a3CVA22dJyv5YQEkTThU7.jpg"
		}
	},
	{
		"model": "movies.actor",
		"pk": 20049,
		"fields": {
			"name": "데이비드 테넌트",
			"profile_path": "/zM76EBPZkdkSHyESyIUa47aP87R.jpg"
		}
	},
	{
		"model": "movies.actor",
		"pk": 93801,
		"fields": {
			"name": "카미야 히로시",
			"profile_path": "/u2r0u8tOa0cyh7nawcEOPpcEZr1.jpg"
		}
	},
	{
		"model": "movies.actor",
		"pk": 11916,
		"fields": {
			"name": "리브 울만",
			"profile_path": "/55dWq9huV2qLaFbc8ZkDq0iz4iD.jpg"
		}
	},
	{
		"model": "movies.actor",
		"pk": 151182,
		"fields": {
			"name": "쿠노 미사키",
			"profile_path": "/hVtE4gdKaqofYZmXXtlJs4Q9XTL.jpg"
		}
	},
	{
		"model": "movies.actor",
		"pk": 1027740,
		"fields": {
			"name": "파코 토우스",
			"profile_path": "/uDGKTKKv9v2JRutCZJjKwpJVKOs.jpg"
		}
	},
	{
		"model": "movies.actor",
		"pk": 1289968,
		"fields": {
			"name": "카라 델레바인",
			"profile_path": "/fxpve7evj6H1kl8rTnDqNyIdObI.jpg"
		}
	},
	{
		"model": "movies.actor",
		"pk": 1560335,
		"fields": {
			"name": "수린 안사리",
			"profile_path": "/lJuW2N6JhG2GJTulmkJYzQXvhvA.jpg"
		}
	},
	{
		"model": "movies.actor",
		"pk": 12052,
		"fields": {
			"name": "귀네스 팰트로",
			"profile_path": "/slPWN0VvYJtNOEuxlFSsXSNQMaF.jpg"
		}
	},
	{
		"model": "movies.actor",
		"pk": 3872,
		"fields": {
			"name": "다니엘 브륄",
			"profile_path": "/3YlmTfiy5qZXkrdKGjaM1uMjGKP.jpg"
		}
	},
	{
		"model": "movies.actor",
		"pk": 12074,
		"fields": {
			"name": "존 리스고",
			"profile_path": "/eNPYHaQz3QCl4ebhJyHdI3KGe6F.jpg"
		}
	},
	{
		"model": "movies.actor",
		"pk": 3894,
		"fields": {
			"name": "크리스찬 베일",
			"profile_path": "/qCpZn2e3dimwbryLnqxZuI88PTi.jpg"
		}
	},
	{
		"model": "movies.actor",
		"pk": 3895,
		"fields": {
			"name": "마이클 케인",
			"profile_path": "/hZruclwEPCKw3e83rnFSIH5sRFZ.jpg"
		}
	},
	{
		"model": "movies.actor",
		"pk": 3896,
		"fields": {
			"name": "리암 니슨",
			"profile_path": "/bboldwqSC6tdw2iL6631c98l2Mn.jpg"
		}
	},
	{
		"model": "movies.actor",
		"pk": 3899,
		"fields": {
			"name": "와타나베 켄",
			"profile_path": "/psAXOYp9SBOXvg6AXzARDedNQ9P.jpg"
		}
	},
	{
		"model": "movies.actor",
		"pk": 2256705,
		"fields": {
			"name": "폰 루이스",
			"profile_path": "/bD92UEjqBKe3Tu075Ww8BENDCaO.jpg"
		}
	},
	{
		"model": "movies.actor",
		"pk": 2256709,
		"fields": {
			"name": "매기 닉슨",
			"profile_path": "/8TgkYPwmsjZkkcS9OJSeY3Hc4RC.jpg"
		}
	},
	{
		"model": "movies.actor",
		"pk": 20331,
		"fields": {
			"name": "다나카 유코",
			"profile_path": "/xXek6ZKG9iH5ughIneW3yv9slyY.jpg"
		}
	},
	{
		"model": "movies.actor",
		"pk": 20333,
		"fields": {
			"name": "니시무라 마사히코",
			"profile_path": "/2fXvxAI4KySYgp9KZMzkK4q2TkY.jpg"
		}
	},
	{
		"model": "movies.actor",
		"pk": 1544084,
		"fields": {
			"name": "김남준",
			"profile_path": "/cJmaUOIuibsC0DPnUMStN4rfAwr.jpg"
		}
	},
	{
		"model": "movies.actor",
		"pk": 20374,
		"fields": {
			"name": "테레사 팔머",
			"profile_path": "/sjSiLSCp9LS1Z0nyGpmquTBuUyr.jpg"
		}
	},
	{
		"model": "movies.actor",
		"pk": 1544086,
		"fields": {
			"name": "민윤기",
			"profile_path": "/83xf9EkLK3k7CJSaXe3iVgBC6S3.jpg"
		}
	},
	{
		"model": "movies.actor",
		"pk": 1544088,
		"fields": {
			"name": "진",
			"profile_path": "/cothCnRmZXC63olRZ816lZoGMDc.jpg"
		}
	},
	{
		"model": "movies.actor",
		"pk": 1544090,
		"fields": {
			"name": "정호석",
			"profile_path": "/2xZu36Z6JFT95AIzazyRHW51dC1.jpg"
		}
	},
	{
		"model": "movies.actor",
		"pk": 1806235,
		"fields": {
			"name": "김성경",
			"profile_path": "/xsH2yoY7K2pWjQ5vIMetMrXenV2.jpg"
		}
	},
	{
		"model": "movies.actor",
		"pk": 1544092,
		"fields": {
			"name": "지민",
			"profile_path": "/ydSiyzoGcjvNLXwXm6dhIFxAewN.jpg"
		}
	},
	{
		"model": "movies.actor",
		"pk": 1544093,
		"fields": {
			"name": "김태형",
			"profile_path": "/jPCklfz8cAXfvRptmeNeYBa9Myf.jpg"
		}
	},
	{
		"model": "movies.actor",
		"pk": 1544095,
		"fields": {
			"name": "정국",
			"profile_path": "/2O7wrPFZtdfNJ5w6LGlIri3Xd0.jpg"
		}
	},
	{
		"model": "movies.actor",
		"pk": 4070,
		"fields": {
			"name": "그레이스 켈리",
			"profile_path": "/3tYufv33dqbnK8IzV4hdsolndO0.jpg"
		}
	},
	{
		"model": "movies.actor",
		"pk": 4078,
		"fields": {
			"name": "리 밴 클리프",
			"profile_path": "/prcDQR2pp0b92j0G8rnX5kQeQk0.jpg"
		}
	},
	{
		"model": "movies.actor",
		"pk": 4090,
		"fields": {
			"name": "셜리 매클레인",
			"profile_path": "/mpW9c34IAFPW0ODuKR8J0FAqN5i.jpg"
		}
	},
	{
		"model": "movies.actor",
		"pk": 4111,
		"fields": {
			"name": "잉그리드 버그먼",
			"profile_path": "/ncKMKRkK5JpCZ2c4A5e9erN8w0j.jpg"
		}
	},
	{
		"model": "movies.actor",
		"pk": 86034,
		"fields": {
			"name": "줄리앤 니콜슨",
			"profile_path": "/2RJ30pPSQQxteuoMjhN1FWTwxlZ.jpg"
		}
	},
	{
		"model": "movies.actor",
		"pk": 1249310,
		"fields": {
			"name": "코토부키 미나코",
			"profile_path": "/puocmMfvql6X1AvhFTolaV6Vh2r.jpg"
		}
	},
	{
		"model": "movies.actor",
		"pk": 20508,
		"fields": {
			"name": "이아인 글렌",
			"profile_path": "/n9zXQhjtXQnc30kqF66hdX4i3PG.jpg"
		}
	},
	{
		"model": "movies.actor",
		"pk": 4139,
		"fields": {
			"name": "톰 스커릿",
			"profile_path": "/fzfFrbdRPnAYaE0h3OD1PsMtiy8.jpg"
		}
	},
	{
		"model": "movies.actor",
		"pk": 110665,
		"fields": {
			"name": "나미카와 다이스케",
			"profile_path": "/iw0X8oDutxaBAri3Ifga8nhdUJK.jpg"
		}
	},
	{
		"model": "movies.actor",
		"pk": 4173,
		"fields": {
			"name": "앤서니 홉킨스",
			"profile_path": "/9ukJS2QWTJ22HcwR1ktMmoJ6RSL.jpg"
		}
	},
	{
		"model": "movies.actor",
		"pk": 20577,
		"fields": {
			"name": "아미라 카서",
			"profile_path": "/nWsXy5uWURGUKlv5i49L2EQPEEg.jpg"
		}
	},
	{
		"model": "movies.actor",
		"pk": 77931,
		"fields": {
			"name": "미츠이시 코토노",
			"profile_path": "/mvKgkuAVVMmjkFWlwVQu8KCa80O.jpg"
		}
	},
	{
		"model": "movies.actor",
		"pk": 233590,
		"fields": {
			"name": "마츠오카 요시츠구",
			"profile_path": "/ugDwdWEXnmv43jcbnfAi4XwiQ8C.jpg"
		}
	},
	{
		"model": "movies.actor",
		"pk": 3281025,
		"fields": {
			"name": "김누림",
			"profile_path": "/qGJjHHCeW0DcwpFvfDoERxmBulj.jpg"
		}
	},
	{
		"model": "movies.actor",
		"pk": 53431,
		"fields": {
			"name": "나딘 라바키",
			"profile_path": "/xfl6idMSJWNU2w7BAGowoamivor.jpg"
		}
	},
	{
		"model": "movies.actor",
		"pk": 118976,
		"fields": {
			"name": "김동욱",
			"profile_path": "/kaPpIz331j9sWGEs9IwCWGqoUa.jpg"
		}
	},
	{
		"model": "movies.actor",
		"pk": 2117890,
		"fields": {
			"name": "변우석",
			"profile_path": "/zncWneej0zzw340EimyM39EWVvj.jpg"
		}
	},
	{
		"model": "movies.actor",
		"pk": 20738,
		"fields": {
			"name": "송강호",
			"profile_path": "/dyWUKQlNyr7SUAjo58VZXvPODkr.jpg"
		}
	},
	{
		"model": "movies.actor",
		"pk": 37153,
		"fields": {
			"name": "조이 크래비츠",
			"profile_path": "/tiQ3TBSvU4YAyrWMmVk6MTrKBAi.jpg"
		}
	},
	{
		"model": "movies.actor",
		"pk": 2158882,
		"fields": {
			"name": "장혜진",
			"profile_path": "/pZiQXSWwo9F4gncHfa1yw0CQjxk.jpg"
		}
	},
	{
		"model": "movies.actor",
		"pk": 119143,
		"fields": {
			"name": "하나자와 카나",
			"profile_path": "/5bK9ttcRydQBWmyZp7gXDmJYOPF.jpg"
		}
	},
	{
		"model": "movies.actor",
		"pk": 119145,
		"fields": {
			"name": "시모노 히로",
			"profile_path": "/i5CaaqKmHH0vKCloqZyrCwn5mWy.jpg"
		}
	},
	{
		"model": "movies.actor",
		"pk": 1315198,
		"fields": {
			"name": "야마모토 카네히라",
			"profile_path": "/8cDkO8oCkqsPliIqwFdnmJqHzDT.jpg"
		}
	},
	{
		"model": "movies.actor",
		"pk": 12670,
		"fields": {
			"name": "기무라 타쿠야",
			"profile_path": "/rafirRSsSsZrSVV3znCUwwSGIGr.jpg"
		}
	},
	{
		"model": "movies.actor",
		"pk": 53650,
		"fields": {
			"name": "앤소니 맥키",
			"profile_path": "/kfTwOYr3iUucmYz8kPjhYy07G2Z.jpg"
		}
	},
	{
		"model": "movies.actor",
		"pk": 4512,
		"fields": {
			"name": "제임스 우즈",
			"profile_path": "/tLH7mpH4KqkWL5VgjueTbewGsfK.jpg"
		}
	},
	{
		"model": "movies.actor",
		"pk": 4517,
		"fields": {
			"name": "조 페시",
			"profile_path": "/4AO0Rwdg2ky8Usmgzgj0dvhy7Zw.jpg"
		}
	},
	{
		"model": "movies.actor",
		"pk": 225730,
		"fields": {
			"name": "카미키 류노스케",
			"profile_path": "/6MwcfIUraHuKOmwjT4gX8BBB2T6.jpg"
		}
	},
	{
		"model": "movies.actor",
		"pk": 119243,
		"fields": {
			"name": "스가와라 분타",
			"profile_path": "/lHPLlP8zNwGMmcUI8rGks5vp8Vn.jpg"
		}
	},
	{
		"model": "movies.actor",
		"pk": 1241566,
		"fields": {
			"name": "사토 리나",
			"profile_path": "/c79SXutqQ02zaGi07sqWCbO96re.jpg"
		}
	},
	{
		"model": "movies.actor",
		"pk": 1241611,
		"fields": {
			"name": "사토 사토미",
			"profile_path": "/o0Aueg2zc3E8ojbguo8Tbd1oAyB.jpg"
		}
	},
	{
		"model": "movies.actor",
		"pk": 12833,
		"fields": {
			"name": "에드워드 번즈",
			"profile_path": "/i68I0bNcNd9i88cMQYQvKxX3gBr.jpg"
		}
	},
	{
		"model": "movies.actor",
		"pk": 12834,
		"fields": {
			"name": "배리 페퍼",
			"profile_path": "/pmdNUqrpsoozh7QYqUgEgZQ69cA.jpg"
		}
	},
	{
		"model": "movies.actor",
		"pk": 1643043,
		"fields": {
			"name": "초슨 제이콥스",
			"profile_path": "/uMmg0hSYO65B4m0fJN3aDvXw8tw.jpg"
		}
	},
	{
		"model": "movies.actor",
		"pk": 12835,
		"fields": {
			"name": "빈 디젤",
			"profile_path": "/7rwSXluNWZAluYMOEWBxkPmckES.jpg"
		}
	},
	{
		"model": "movies.actor",
		"pk": 12836,
		"fields": {
			"name": "테드 댄슨",
			"profile_path": "/2QUEYVhrKbOkRKeFEUnc5sJby6a.jpg"
		}
	},
	{
		"model": "movies.actor",
		"pk": 4654,
		"fields": {
			"name": "제레미 데이비스",
			"profile_path": "/y9GhiLVrVFkJqs0wXqJTcvpOBLb.jpg"
		}
	},
	{
		"model": "movies.actor",
		"pk": 53807,
		"fields": {
			"name": "아미 해머",
			"profile_path": "/dacZbbnheEhejYbkDgz7WhhSBJp.jpg"
		}
	},
	{
		"model": "movies.actor",
		"pk": 2019916,
		"fields": {
			"name": "나카자와 마사토모",
			"profile_path": "/3pezOVWCMKWdqAzwSo0eKNtso95.jpg"
		}
	},
	{
		"model": "movies.actor",
		"pk": 78423,
		"fields": {
			"name": "오마르 시",
			"profile_path": "/laNZay6AfEzvEvY1NUH9UFiSD0a.jpg"
		}
	},
	{
		"model": "movies.actor",
		"pk": 4808,
		"fields": {
			"name": "지안카를로 에스포지토",
			"profile_path": "/lBvDQZjxhIGMbH61iHnqerpbqHc.jpg"
		}
	},
	{
		"model": "movies.actor",
		"pk": 13022,
		"fields": {
			"name": "톰 베린저",
			"profile_path": "/zLxzAdAfu7y02yEx29JSLDgXJZ4.jpg"
		}
	},
	{
		"model": "movies.actor",
		"pk": 299743,
		"fields": {
			"name": "세바스찬 마니스칼코",
			"profile_path": "/bvJQGVOI8fJ9Y4eAvYqoQcOAbHZ.jpg"
		}
	},
	{
		"model": "movies.actor",
		"pk": 78577,
		"fields": {
			"name": "그레이엄 노튼",
			"profile_path": "/2VLkmia1Nd6r78WM5vWDgIIVsDF.jpg"
		}
	},
	{
		"model": "movies.actor",
		"pk": 37625,
		"fields": {
			"name": "앤드류 가필드",
			"profile_path": "/9hJ59ogLxgcZDkvfGcjLHqbB5Pl.jpg"
		}
	},
	{
		"model": "movies.actor",
		"pk": 1299243,
		"fields": {
			"name": "엄지원",
			"profile_path": "/tpWZnjZUREwMSzCbKbGPI6DVUdw.jpg"
		}
	},
	{
		"model": "movies.actor",
		"pk": 1299244,
		"fields": {
			"name": "이레",
			"profile_path": "/i1A5E4v5xRFammipC3H4jeOwczv.jpg"
		}
	},
	{
		"model": "movies.actor",
		"pk": 21316,
		"fields": {
			"name": "네스터 카보넬",
			"profile_path": "/wAk4Me2INiNSpRvzU8K98743Uc1.jpg"
		}
	},
	{
		"model": "movies.actor",
		"pk": 4937,
		"fields": {
			"name": "빈스 본",
			"profile_path": "/A9fJ88dfXZGpgFTnQIK0bOtjMrj.jpg"
		}
	},
	{
		"model": "movies.actor",
		"pk": 1700685,
		"fields": {
			"name": "루이스 풀먼",
			"profile_path": "/jAo0Rxl9EYVxLnhUlBww5Uxl89v.jpg"
		}
	},
	{
		"model": "movies.actor",
		"pk": 1299277,
		"fields": {
			"name": "남일우",
			"profile_path": "/tlwjKNRJ4N4hsjYjQcjlXGRKK2O.jpg"
		}
	},
	{
		"model": "movies.actor",
		"pk": 4959,
		"fields": {
			"name": "클라우디아 카르디날레",
			"profile_path": "/eSNCcnxtBJf0AIAB4k7jpFJNwcD.jpg"
		}
	},
	{
		"model": "movies.actor",
		"pk": 62318,
		"fields": {
			"name": "미키 신이치로",
			"profile_path": "/yL9Tx2HZgK7t5AssYl6oGE9bjdj.jpg"
		}
	},
	{
		"model": "movies.actor",
		"pk": 1299317,
		"fields": {
			"name": "강혜정",
			"profile_path": "/46RDs0JLTEmI9Fp6hzU50LmJqId.jpg"
		}
	},
	{
		"model": "movies.actor",
		"pk": 2306987,
		"fields": {
			"name": "정현준",
			"profile_path": "/vZadA6ip6V2kh0VZW9RwnLcYFgW.jpg"
		}
	},
	{
		"model": "movies.actor",
		"pk": 168875,
		"fields": {
			"name": "게리 윅스",
			"profile_path": "/n4taftpteF6qUTeYRDkdGPHC58.jpg"
		}
	},
	{
		"model": "movies.actor",
		"pk": 13240,
		"fields": {
			"name": "마크 월버그",
			"profile_path": "/bTEFpaWd7A6AZVWOqKKBWzKEUe8.jpg"
		}
	},
	{
		"model": "movies.actor",
		"pk": 5049,
		"fields": {
			"name": "존 허트",
			"profile_path": "/wGDGhBOggA8I2ktgc1QoHABEF0m.jpg"
		}
	},
	{
		"model": "movies.actor",
		"pk": 13242,
		"fields": {
			"name": "폴 지아마티",
			"profile_path": "/wbrVVJRr5TwhDZuvijBgOorzcAb.jpg"
		}
	},
	{
		"model": "movies.actor",
		"pk": 1004565,
		"fields": {
			"name": "임원희",
			"profile_path": "/ve0gjj2cf3t4pgrhLKvyavqgq98.jpg"
		}
	},
	{
		"model": "movies.actor",
		"pk": 226366,
		"fields": {
			"name": "브라이언 타이리 헨리",
			"profile_path": "/1UgDnFt3OteCJQPiUelWzIR5bvT.jpg"
		}
	},
	{
		"model": "movies.actor",
		"pk": 1152083,
		"fields": {
			"name": "사브리나 카펜터",
			"profile_path": "/2zAdQGwdnVsKbmpktJ7VCfJbrJy.jpg"
		}
	},
	{
		"model": "movies.actor",
		"pk": 21657,
		"fields": {
			"name": "베라 파미가",
			"profile_path": "/5Vs7huBmTKftwlsc2BPAntyaQYj.jpg"
		}
	},
	{
		"model": "movies.actor",
		"pk": 5293,
		"fields": {
			"name": "윌렘 데포",
			"profile_path": "/ui8e4sgZAwMPi3hzEO53jyBJF9B.jpg"
		}
	},
	{
		"model": "movies.actor",
		"pk": 980225,
		"fields": {
			"name": "라미란",
			"profile_path": "/oNLgdklQkcLwSw6NwGEfFvXN1nY.jpg"
		}
	},
	{
		"model": "movies.actor",
		"pk": 144648,
		"fields": {
			"name": "치하라 미노리",
			"profile_path": "/qSqXpdLUq4prPtL7mkp0go6SbrF.jpg"
		}
	},
	{
		"model": "movies.actor",
		"pk": 144655,
		"fields": {
			"name": "스기타 토모카즈",
			"profile_path": "/cv5zuPZySNsHXu24pjKLYCRzJ2J.jpg"
		}
	},
	{
		"model": "movies.actor",
		"pk": 95504,
		"fields": {
			"name": "하라 세츠코",
			"profile_path": "/zaiy9COvjUVGV6q9x7ptuZeuTCa.jpg"
		}
	},
	{
		"model": "movies.actor",
		"pk": 136532,
		"fields": {
			"name": "맷 스미스",
			"profile_path": "/b3AYe7kkImkB35CoYwlUqHnJGF8.jpg"
		}
	},
	{
		"model": "movies.actor",
		"pk": 554330,
		"fields": {
			"name": "이승신",
			"profile_path": "/vYbx7qS6H3BXLmdIsggJKulEVaY.jpg"
		}
	},
	{
		"model": "movies.actor",
		"pk": 996701,
		"fields": {
			"name": "마일즈 텔러",
			"profile_path": "/cg3LW0xX6RKr8dmescxq1bepcb5.jpg"
		}
	},
	{
		"model": "movies.actor",
		"pk": 71070,
		"fields": {
			"name": "아만다 사이프리드",
			"profile_path": "/wcHYErlynY8xWe6X7RmqEqpMBGl.jpg"
		}
	},
	{
		"model": "movies.actor",
		"pk": 54693,
		"fields": {
			"name": "엠마 스톤",
			"profile_path": "/cZ8a3QvAnj2cgcgVL6g4XaqPzpL.jpg"
		}
	},
	{
		"model": "movies.actor",
		"pk": 1324470,
		"fields": {
			"name": "타도코로 아즈사",
			"profile_path": "/2VgXgV6rdFPI4QctgJP5qWhHT4x.jpg"
		}
	},
	{
		"model": "movies.actor",
		"pk": 5576,
		"fields": {
			"name": "발 킬머",
			"profile_path": "/szMi36EOoCuMYeYO9eYqRefEnKo.jpg"
		}
	},
	{
		"model": "movies.actor",
		"pk": 1545693,
		"fields": {
			"name": "자시 비츠",
			"profile_path": "/ijrT4pvALvxU0gphea4YxDnDh6e.jpg"
		}
	},
	{
		"model": "movies.actor",
		"pk": 1168909,
		"fields": {
			"name": "토야마 나오",
			"profile_path": "/1tl5iuYb2VvCfTzC9iPaBxASrXs.jpg"
		}
	},
	{
		"model": "movies.actor",
		"pk": 13848,
		"fields": {
			"name": "찰리 채플린",
			"profile_path": "/lRI9Ky1SMOehn04OqhYJ5hQfgIK.jpg"
		}
	},
	{
		"model": "movies.actor",
		"pk": 5659,
		"fields": {
			"name": "세우 조르지",
			"profile_path": "/iJ0TWspJRxanKdUnQraAxjmTCl2.jpg"
		}
	},
	{
		"model": "movies.actor",
		"pk": 1054260,
		"fields": {
			"name": "쿠로키 하루",
			"profile_path": "/rTxASkiwbxohT0UVHORLmECo53Y.jpg"
		}
	},
	{
		"model": "movies.actor",
		"pk": 972356,
		"fields": {
			"name": "루크 브레이시",
			"profile_path": "/ot2h7IrXpC8XSnIZDSVsj2FQ5cx.jpg"
		}
	},
	{
		"model": "movies.actor",
		"pk": 587350,
		"fields": {
			"name": "와타나베 아케노",
			"profile_path": "/4E05IJxvTGNHb2GSaiyxbCZ5nd8.jpg"
		}
	},
	{
		"model": "movies.actor",
		"pk": 13936,
		"fields": {
			"name": "프랭키 페이슨",
			"profile_path": "/3717JOXK2Z8qelfyvScDGimfFBf.jpg"
		}
	},
	{
		"model": "movies.actor",
		"pk": 1324666,
		"fields": {
			"name": "이시카와 카이토",
			"profile_path": "/kLVhJYH73ust9ComUxGR63DOvxu.jpg"
		}
	},
	{
		"model": "movies.actor",
		"pk": 1128106,
		"fields": {
			"name": "김향기",
			"profile_path": "/qAfGNnSzuSRVISUtLssokeHtoWy.jpg"
		}
	},
	{
		"model": "movies.actor",
		"pk": 5814,
		"fields": {
			"name": "루이지 피스틸리",
			"profile_path": "/bH5vmD2CMBHzJyBe0P0bL6iTUNL.jpg"
		}
	},
	{
		"model": "movies.actor",
		"pk": 145092,
		"fields": {
			"name": "주동우",
			"profile_path": "/vD2vVvIIx8ygzkhUQZJLkvYT1jr.jpg"
		}
	},
	{
		"model": "movies.actor",
		"pk": 22226,
		"fields": {
			"name": "폴 러드",
			"profile_path": "/8eTtJ7XVXY0BnEeUaSiTAraTIXd.jpg"
		}
	},
	{
		"model": "movies.actor",
		"pk": 1537768,
		"fields": {
			"name": "김태리",
			"profile_path": "/gFofVUeVlIvBJMUv7maHQwWdfsk.jpg"
		}
	},
	{
		"model": "movies.actor",
		"pk": 55061,
		"fields": {
			"name": "카졸",
			"profile_path": "/h4m0TkDuEMCUNaPrQxMRyFb2AQ7.jpg"
		}
	},
	{
		"model": "movies.actor",
		"pk": 1136406,
		"fields": {
			"name": "톰 홀랜드",
			"profile_path": "/bBRlrpJm9XkNSg0YT5LCaxqoFMX.jpg"
		}
	},
	{
		"model": "movies.actor",
		"pk": 5916,
		"fields": {
			"name": "로자리오 도슨",
			"profile_path": "/wOl6QskSwla4tWv4ZWlmSwz7S7U.jpg"
		}
	},
	{
		"model": "movies.actor",
		"pk": 87932,
		"fields": {
			"name": "르네 엘리스 골즈베리",
			"profile_path": "/p4Rjbr8ZpQ7l3qVCGvNqrLlPs4M.jpg"
		}
	},
	{
		"model": "movies.actor",
		"pk": 120724,
		"fields": {
			"name": "제이든 스미스",
			"profile_path": "/meraACSN0LYwLeZlaXN9YW6JCZT.jpg"
		}
	},
	{
		"model": "movies.actor",
		"pk": 587675,
		"fields": {
			"name": "유연석",
			"profile_path": "/mER9G7T2ObjAshrASI5rVPUeYaB.jpg"
		}
	},
	{
		"model": "movies.actor",
		"pk": 71580,
		"fields": {
			"name": "베네딕트 컴버배치",
			"profile_path": "/wz3MRiMmoz6b5X3oSzMRC9nLxY1.jpg"
		}
	},
	{
		"model": "movies.actor",
		"pk": 186341,
		"fields": {
			"name": "사와시로 미유키",
			"profile_path": "/3l2HIkVifapvSPPGYZO4oI5snXk.jpg"
		}
	},
	{
		"model": "movies.actor",
		"pk": 1325034,
		"fields": {
			"name": "아마미야 소라",
			"profile_path": "/4ZZcdFH4QgbIC8AeJ3BLG1ue7G5.jpg"
		}
	},
	{
		"model": "movies.actor",
		"pk": 6161,
		"fields": {
			"name": "제니퍼 코넬리",
			"profile_path": "/egh1eOHuYgeoqdlLQgaXMl6cPOm.jpg"
		}
	},
	{
		"model": "movies.actor",
		"pk": 6163,
		"fields": {
			"name": "아담 골드버그",
			"profile_path": "/hiqnMk1ojxuboipcsLzNbf0cloK.jpg"
		}
	},
	{
		"model": "movies.actor",
		"pk": 6193,
		"fields": {
			"name": "레오나르도 디카프리오",
			"profile_path": "/wo2hJpn04vbtmh0B9utCFdsQhxM.jpg"
		}
	},
	{
		"model": "movies.actor",
		"pk": 202806,
		"fields": {
			"name": "호리에 유이",
			"profile_path": "/73yQlMWaiOMrhvPCNyOCbbCkILZ.jpg"
		}
	},
	{
		"model": "movies.actor",
		"pk": 1488961,
		"fields": {
			"name": "릴렐 호워리",
			"profile_path": "/9MDi35Fy6ym7SYbO3B04vf1vBnm.jpg"
		}
	},
	{
		"model": "movies.actor",
		"pk": 104522,
		"fields": {
			"name": "미야자키 아오이",
			"profile_path": "/8J2i8Da2FmqMsDqSlndEpzkPQYd.jpg"
		}
	},
	{
		"model": "movies.actor",
		"pk": 129104,
		"fields": {
			"name": "멜리사 베노이스트",
			"profile_path": "/tmJsadF5ujTypPZtO54HsXTup3J.jpg"
		}
	},
	{
		"model": "movies.actor",
		"pk": 3553480,
		"fields": {
			"name": "곽은진",
			"profile_path": null
		}
	},
	{
		"model": "movies.actor",
		"pk": 39187,
		"fields": {
			"name": "올리비아 콜먼",
			"profile_path": "/1KTXGJaqWRnsoA6qeaUa7U2zkHL.jpg"
		}
	},
	{
		"model": "movies.actor",
		"pk": 6614,
		"fields": {
			"name": "콜 하우저",
			"profile_path": "/4cLTfmwGXOjgXOavjQyCLA36hIM.jpg"
		}
	},
	{
		"model": "movies.actor",
		"pk": 6637,
		"fields": {
			"name": "프랭크 핀레이",
			"profile_path": "/fz3sIozTo0L1eCKlwHdoe92dcXk.jpg"
		}
	},
	{
		"model": "movies.actor",
		"pk": 6638,
		"fields": {
			"name": "모린 립먼",
			"profile_path": "/kx26NOAw9GnsHjJIJ4l40YHblJ.jpg"
		}
	},
	{
		"model": "movies.actor",
		"pk": 6639,
		"fields": {
			"name": "에밀리아 폭스",
			"profile_path": "/lZpNRsHAOW8m0f7bRfgUDmRRjo.jpg"
		}
	},
	{
		"model": "movies.actor",
		"pk": 219659,
		"fields": {
			"name": "테라소마 마사키",
			"profile_path": "/eol7Ul4buAam9SmJDuFIWln0Cd3.jpg"
		}
	},
	{
		"model": "movies.actor",
		"pk": 6692,
		"fields": {
			"name": "캐롤라인 구덜",
			"profile_path": "/4cagGtMqACvkuw6Llq8Li8UJ1AR.jpg"
		}
	},
	{
		"model": "movies.actor",
		"pk": 219752,
		"fields": {
			"name": "타카하시 히로키",
			"profile_path": "/8vC4fuIORjrgFcXle4bjgDeaNhE.jpg"
		}
	},
	{
		"model": "movies.actor",
		"pk": 14974,
		"fields": {
			"name": "바바라 스탠윅",
			"profile_path": "/y9BX4FNoFBjP2HPcs8rlzqXjJbu.jpg"
		}
	},
	{
		"model": "movies.actor",
		"pk": 6807,
		"fields": {
			"name": "샘 록웰",
			"profile_path": "/vYpWxV0bnUgKo7SdasfGP9HttUq.jpg"
		}
	},
	{
		"model": "movies.actor",
		"pk": 1694435,
		"fields": {
			"name": "박명훈",
			"profile_path": "/8IgD7YBQKi2K94RSCwXCCrKcQrA.jpg"
		}
	},
	{
		"model": "movies.actor",
		"pk": 6944,
		"fields": {
			"name": "옥타비아 스펜서",
			"profile_path": "/zDGydyM1fmvNWzQlTAns9IZjNxT.jpg"
		}
	},
	{
		"model": "movies.actor",
		"pk": 1563442,
		"fields": {
			"name": "키토 아카리",
			"profile_path": "/43SgANYtj7vpsHmz68hgPDlxC15.jpg"
		}
	},
	{
		"model": "movies.actor",
		"pk": 1325949,
		"fields": {
			"name": "이노링",
			"profile_path": "/sSXB0DOmfLy1BGsTN7q98Q9yzAf.jpg"
		}
	},
	{
		"model": "movies.actor",
		"pk": 1325962,
		"fields": {
			"name": "야마시타 다이키",
			"profile_path": "/rQNdJdZewk7VGP16ZNbpfJ9ZeMd.jpg"
		}
	},
	{
		"model": "movies.actor",
		"pk": 7071,
		"fields": {
			"name": "루이즈 플레쳐",
			"profile_path": "/hN15em5LqXqDe1QgDa6lXK9fx3z.jpg"
		}
	},
	{
		"model": "movies.actor",
		"pk": 7132,
		"fields": {
			"name": "빈센트 도노프리오",
			"profile_path": "/qkyiLolEqYMGH25xD4sFIXAjZQB.jpg"
		}
	},
	{
		"model": "movies.actor",
		"pk": 56323,
		"fields": {
			"name": "티나 페이",
			"profile_path": "/yPTAi1iucXf85UpiFPtyiTSM6do.jpg"
		}
	},
	{
		"model": "movies.actor",
		"pk": 3218480,
		"fields": {
			"name": "노윤서",
			"profile_path": "/A67wGhTozfav5saZ1Umi5f98Ezb.jpg"
		}
	},
	{
		"model": "movies.actor",
		"pk": 1326155,
		"fields": {
			"name": "강신철",
			"profile_path": "/rTgi7u8XdfxyeZHGIYFPKpnrJGc.jpg"
		}
	},
	{
		"model": "movies.actor",
		"pk": 138336,
		"fields": {
			"name": "조진웅",
			"profile_path": "/r3o7eKsqVCQu0ppIY88d16VLCsj.jpg"
		}
	},
	{
		"model": "movies.actor",
		"pk": 932967,
		"fields": {
			"name": "마허샬라 알리",
			"profile_path": "/9ZmSejm5lnUVY5IJ1iNx2QEjnHb.jpg"
		}
	},
	{
		"model": "movies.actor",
		"pk": 72873,
		"fields": {
			"name": "마이클 스털버그",
			"profile_path": "/aYB3SQm3h6ZyAdlbGyiNfakjx56.jpg"
		}
	},
	{
		"model": "movies.actor",
		"pk": 15555,
		"fields": {
			"name": "파이퍼 페라보",
			"profile_path": "/aP9QqLm4JZxLwp2CiUbEh5zrpVI.jpg"
		}
	},
	{
		"model": "movies.actor",
		"pk": 15556,
		"fields": {
			"name": "레베카 홀",
			"profile_path": "/cVZaQrUY7F5khCBYdKDlEppHnQi.jpg"
		}
	},
	{
		"model": "movies.actor",
		"pk": 1014991,
		"fields": {
			"name": "토요나가 토시유키",
			"profile_path": "/vFMsZOYZqkojgBWKmpFG4hrFrWN.jpg"
		}
	},
	{
		"model": "movies.actor",
		"pk": 1080542,
		"fields": {
			"name": "제나 콜먼",
			"profile_path": "/pylSrUkaLzDvfflyMnU32eY0vrN.jpg"
		}
	},
	{
		"model": "movies.actor",
		"pk": 1277188,
		"fields": {
			"name": "제이콥 트렘블레이",
			"profile_path": "/oNLhzkZXNw1RNihne9P5q57cRcd.jpg"
		}
	},
	{
		"model": "movies.actor",
		"pk": 7447,
		"fields": {
			"name": "앨릭 볼드윈",
			"profile_path": "/hzKy7x574eeUS3wt1R3yvWBRpeR.jpg"
		}
	},
	{
		"model": "movies.actor",
		"pk": 7451,
		"fields": {
			"name": "쿄 마치코",
			"profile_path": "/24tQVUgGN4s6rp1P9qlnT74RSJI.jpg"
		}
	},
	{
		"model": "movies.actor",
		"pk": 7497,
		"fields": {
			"name": "홀트 맥칼라니",
			"profile_path": "/a5ax2ICLrV6l0T74OSFvzssCQyQ.jpg"
		}
	},
	{
		"model": "movies.actor",
		"pk": 7498,
		"fields": {
			"name": "에이온 바일리",
			"profile_path": "/hKqfGq1sPhZdQOlto0bS3igFZdP.jpg"
		}
	},
	{
		"model": "movies.actor",
		"pk": 7499,
		"fields": {
			"name": "자레드 레토",
			"profile_path": "/lZaE3x8yxofNZ96xpthxuVXQxTM.jpg"
		}
	},
	{
		"model": "movies.actor",
		"pk": 1998163,
		"fields": {
			"name": "전혜원",
			"profile_path": "/iiLAT4wZ1DtPUPA0l8YH9MeXgQS.jpg"
		}
	},
	{
		"model": "movies.actor",
		"pk": 64880,
		"fields": {
			"name": "최민식",
			"profile_path": "/sd7gIA6nEkq6zumkDCfxSE0YSSV.jpg"
		}
	},
	{
		"model": "movies.actor",
		"pk": 40325,
		"fields": {
			"name": "하야시바라 메구미",
			"profile_path": "/cZcdY6N7QbkIyEl3mN5fwtRxSxJ.jpg"
		}
	},
	{
		"model": "movies.actor",
		"pk": 556435,
		"fields": {
			"name": "조여정",
			"profile_path": "/n7YWOoquBL9g3qEwQ2zvrQSW96L.jpg"
		}
	},
	{
		"model": "movies.actor",
		"pk": 56730,
		"fields": {
			"name": "콜 스프로즈",
			"profile_path": "/aJxTvZjse8hAljcvljqTaH45eaB.jpg"
		}
	},
	{
		"model": "movies.actor",
		"pk": 130532,
		"fields": {
			"name": "마이크 해튼",
			"profile_path": "/f1dQlVm0plWWCcFczq4d9jTQUxN.jpg"
		}
	},
	{
		"model": "movies.actor",
		"pk": 24045,
		"fields": {
			"name": "조셉 고든 레빗",
			"profile_path": "/dhv9f3AaozOjpvjAwVzOWlmmT2V.jpg"
		}
	},
	{
		"model": "movies.actor",
		"pk": 1572354,
		"fields": {
			"name": "이정은",
			"profile_path": "/4r3K47UpSmzZ5t9cyTRRqRl9rdz.jpg"
		}
	},
	{
		"model": "movies.actor",
		"pk": 40450,
		"fields": {
			"name": "오오이즈미 요",
			"profile_path": "/qw5KLuww2AEAk6JEssEkJY3wBn1.jpg"
		}
	},
	{
		"model": "movies.actor",
		"pk": 40453,
		"fields": {
			"name": "카토 하루코",
			"profile_path": "/WyeP5PbPEDeQI83Mq1NYwB87mk.jpg"
		}
	},
	{
		"model": "movies.actor",
		"pk": 73249,
		"fields": {
			"name": "이정재",
			"profile_path": "/3h5Cfm0X8ohWn7psZkqdNWqXAHH.jpg"
		}
	},
	{
		"model": "movies.actor",
		"pk": 1613352,
		"fields": {
			"name": "마스다 토시키",
			"profile_path": "/oMAk5Pu3aazmwFwiVOgyU7iW5ut.jpg"
		}
	},
	{
		"model": "movies.actor",
		"pk": 1211946,
		"fields": {
			"name": "번",
			"profile_path": "/sKqr3A3LjLYlRCXJGJI8rjpdMOs.jpg"
		}
	},
	{
		"model": "movies.actor",
		"pk": 130640,
		"fields": {
			"name": "헤일리 스타인펠드",
			"profile_path": "/q4UpZMEuvNCN5lL5L6xa3ICpheJ.jpg"
		}
	},
	{
		"model": "movies.actor",
		"pk": 1203792,
		"fields": {
			"name": "조한철",
			"profile_path": "/sk0pVWe5wOAX6dVRzPkxMysfVWr.jpg"
		}
	},
	{
		"model": "movies.actor",
		"pk": 1072774,
		"fields": {
			"name": "히카사 요코",
			"profile_path": "/e6I7r45YZXgvlEVSGR3L14tSl87.jpg"
		}
	},
	{
		"model": "movies.actor",
		"pk": 73421,
		"fields": {
			"name": "호아킨 피닉스",
			"profile_path": "/1UzIGSKFH0A9ouwnMwQQWUiqV2s.jpg"
		}
	},
	{
		"model": "movies.actor",
		"pk": 2440951,
		"fields": {
			"name": "주야",
			"profile_path": "/z8FT0cY7gJMPX6PNK2mvsdiNoMm.jpg"
		}
	},
	{
		"model": "movies.actor",
		"pk": 237304,
		"fields": {
			"name": "와쿠이 에미",
			"profile_path": "/kQ9nW6YbMOC56BGdc69yLHsYc5D.jpg"
		}
	},
	{
		"model": "movies.actor",
		"pk": 851784,
		"fields": {
			"name": "매켄지 포이",
			"profile_path": "/gW9BdiA9eooBWa5bzHWkV7rbTa8.jpg"
		}
	},
	{
		"model": "movies.actor",
		"pk": 1318732,
		"fields": {
			"name": "타카스기 마히로",
			"profile_path": "/8SHi5gVZEukRAwzhryZmE7RPPnk.jpg"
		}
	},
	{
		"model": "movies.actor",
		"pk": 221098,
		"fields": {
			"name": "안나 캠프",
			"profile_path": "/yOGBODtjYsZnQH8p7dZb0S015Pf.jpg"
		}
	},
	{
		"model": "movies.actor",
		"pk": 1613744,
		"fields": {
			"name": "자 마리노프",
			"profile_path": "/lZwHZ27xqsPsuswcxyx6uWSh5VP.jpg"
		}
	},
	{
		"model": "movies.actor",
		"pk": 24551,
		"fields": {
			"name": "다나카 키누요",
			"profile_path": "/noiEyzOXEtqAEN3zQDEJ10748L6.jpg"
		}
	}
]